{
  "tasks": [
    {
      "id": 1,
      "text": "Buy groceries",
      "day": "Monday",
      "reminder": false
    },
    {
      "id": 2,
      "text": "Do laundry",
      "day": "Tuesday",
      "reminder": false
    },
    {
      "id": 3,
      "text": "Go for a run",
      "day": "Wednesday",
      "reminder": true
    },
    {
      "id": 4,
      "text": "Pay bills",
      "day": "Thursday",
      "reminder": true
    },
    {
      "text": "Bury a friend",
      "day": "Monday",
      "reminder": true,
      "id": 5
    }
  ]
}